[
   {
      "typeArticle":"G",
      "codeArticle":"1148465",
      "libelleArticle":"COFFRET HACHOIR A VIANDE +ACC ",
      "formatEtiquette":"P",
      "nbEtiquettes":1,
      "codeAllee":"C",
      "codeGondole":"N",
      "codeEmplacement":99999,
      "typeCommande":"1",
      "typeFlux":"2",
      "strate":"L",
      "stockMinimum":2,
      "pvm":11.9,
      "stockMiniAutomatique":true,
      "labelCalculAutoStockMiniFamille":"1 - Stock Mini FHP",
      "labelLongCalculAutoStockMiniFamille":"Facing*Hauteur*Profondeur",
      "parametrageCalculAutoStockMiniFamille":true,
      "parametrageCalculAutoStockMiniArticle":true
   },
   {
      "typeArticle":"G",
      "codeArticle":"1376414",
      "libelleArticle":"BOUCHERIE SEA (ABG) 5,5%      ",
      "formatEtiquette":"G",
      "nbEtiquettes":1,
      "codeAllee":"1",
      "codeGondole":"G",
      "codeEmplacement":99999,
      "typeCommande":"2",
      "typeFlux":"2",
      "strate":"L",
      "stockMinimum":2,
      "pvm":1.0,
      "stockMiniAutomatique":false,
      "labelCalculAutoStockMiniFamille":"2 - Stock Mini Max",
      "labelLongCalculAutoStockMiniFamille":"MAX(Fac*Ht*Pf//Vmh/NbLive sem)",
      "parametrageCalculAutoStockMiniFamille":false,
      "parametrageCalculAutoStockMiniArticle":true
   },
   {
      "typeArticle":"G",
      "codeArticle":"1381739",
      "libelleArticle":"CALCULATRICE BUREAU 10 CORA   ",
      "formatEtiquette":"P",
      "nbEtiquettes":1,
      "codeAllee":"A",
      "codeGondole":"N",
      "codeEmplacement":1380,
      "typeCommande":"1",
      "typeFlux":"1",
      "strate":"G",
      "stockMinimum":3,
      "pvm":8.4,
      "stockMiniAutomatique":true,
      "labelCalculAutoStockMiniFamille":"1 - Stock Mini FHP",
      "labelLongCalculAutoStockMiniFamille":"Facing*Hauteur*Profondeur",
      "parametrageCalculAutoStockMiniFamille":true,
      "parametrageCalculAutoStockMiniArticle":true
   },
   {
      "typeArticle":"G",
      "codeArticle":"1381748",
      "libelleArticle":"CALCULATRICE POCHE 8 CORA     ",
      "formatEtiquette":"P",
      "nbEtiquettes":1,
      "codeAllee":"A",
      "codeGondole":"N",
      "codeEmplacement":1370,
      "typeCommande":"1",
      "typeFlux":"1",
      "strate":"M",
      "stockMinimum":3,
      "pvm":3.99,
      "stockMiniAutomatique":true,
      "labelCalculAutoStockMiniFamille":"1 - Stock Mini FHP",
      "labelLongCalculAutoStockMiniFamille":"Facing*Hauteur*Profondeur",
      "parametrageCalculAutoStockMiniFamille":true,
      "parametrageCalculAutoStockMiniArticle":true
   },
   {
      "typeArticle":"G",
      "codeArticle":"0340886",
      "libelleArticle":"COCA COLA STANDARD 4X50CL     ",
      "formatEtiquette":"G",
      "nbEtiquettes":2,
      "codeAllee":"W",
      "codeGondole":"F",
      "codeEmplacement":50,
      "typeCommande":"1",
      "typeFlux":"1",
      "strate":"S",
      "stockMinimum":2,
      "pvm":3.44,
      "stockMiniAutomatique":true,
      "labelCalculAutoStockMiniFamille":"1 - Stock Mini FHP",
      "labelLongCalculAutoStockMiniFamille":"Facing*Hauteur*Profondeur",
      "parametrageCalculAutoStockMiniFamille":true,
      "parametrageCalculAutoStockMiniArticle":true
   },
   {
      "typeArticle":"G",
      "codeArticle":"1482560",
      "libelleArticle":"ANANAS MORCEAU 200 GR         ",
      "formatEtiquette":"G",
      "nbEtiquettes":1,
      "codeAllee":" ",
      "codeGondole":" ",
      "codeEmplacement":0,
      "typeCommande":"2",
      "typeFlux":"1",
      "strate":"L",
      "stockMinimum":2,
      "pvm":2.19,
      "stockMiniAutomatique":false,
      "labelCalculAutoStockMiniFamille":"2 - Stock Mini Max",
      "labelLongCalculAutoStockMiniFamille":"MAX(Fac*Ht*Pf//Vmh/NbLive sem)",
      "parametrageCalculAutoStockMiniFamille":false,
      "parametrageCalculAutoStockMiniArticle":true
   },
   {
      "typeArticle":"G",
      "codeArticle":"1482720",
      "libelleArticle":"MANGUE.MORCEAUX 200G          ",
      "formatEtiquette":"G",
      "nbEtiquettes":1,
      "codeAllee":" ",
      "codeGondole":" ",
      "codeEmplacement":0,
      "typeCommande":"2",
      "typeFlux":"1",
      "strate":"L",
      "stockMinimum":2,
      "pvm":2.39,
      "stockMiniAutomatique":false,
      "labelCalculAutoStockMiniFamille":"2 - Stock Mini Max",
      "labelLongCalculAutoStockMiniFamille":"MAX(Fac*Ht*Pf//Vmh/NbLive sem)",
      "parametrageCalculAutoStockMiniFamille":false,
      "parametrageCalculAutoStockMiniArticle":true
   },
   {
      "typeArticle":"G",
      "codeArticle":"1482737",
      "libelleArticle":"ANANAS, KIWI 350G             ",
      "formatEtiquette":"G",
      "nbEtiquettes":1,
      "codeAllee":" ",
      "codeGondole":" ",
      "codeEmplacement":0,
      "typeCommande":"2",
      "typeFlux":"1",
      "strate":"L",
      "stockMinimum":2,
      "pvm":2.79,
      "stockMiniAutomatique":false,
      "labelCalculAutoStockMiniFamille":"2 - Stock Mini Max",
      "labelLongCalculAutoStockMiniFamille":"MAX(Fac*Ht*Pf//Vmh/NbLive sem)",
      "parametrageCalculAutoStockMiniFamille":false,
      "parametrageCalculAutoStockMiniArticle":true
   },
   {
      "typeArticle":"G",
      "codeArticle":"1482741",
      "libelleArticle":"SALADE DE FRUITS 260G         ",
      "formatEtiquette":"G",
      "nbEtiquettes":1,
      "codeAllee":" ",
      "codeGondole":" ",
      "codeEmplacement":0,
      "typeCommande":"2",
      "typeFlux":"1",
      "strate":"L",
      "stockMinimum":2,
      "pvm":2.29,
      "stockMiniAutomatique":false,
      "labelCalculAutoStockMiniFamille":"2 - Stock Mini Max",
      "labelLongCalculAutoStockMiniFamille":"MAX(Fac*Ht*Pf//Vmh/NbLive sem)",
      "parametrageCalculAutoStockMiniFamille":false,
      "parametrageCalculAutoStockMiniArticle":true
   },
   {
      "typeArticle":"G",
      "codeArticle":"1309984",
      "libelleArticle":"SACS CABAS                    ",
      "formatEtiquette":"G",
      "nbEtiquettes":1,
      "codeAllee":" ",
      "codeGondole":" ",
      "codeEmplacement":0,
      "typeCommande":"2",
      "typeFlux":"2",
      "strate":"L",
      "stockMinimum":2,
      "pvm":1.99,
      "stockMiniAutomatique":true,
      "labelCalculAutoStockMiniFamille":"1 - Stock Mini FHP",
      "labelLongCalculAutoStockMiniFamille":"Facing*Hauteur*Profondeur",
      "parametrageCalculAutoStockMiniFamille":true,
      "parametrageCalculAutoStockMiniArticle":true
   },
   {
      "typeArticle":"G",
      "codeArticle":"1500660",
      "libelleArticle":"JAMBON DE CHEZ NS SUP SC 240G ",
      "formatEtiquette":"P",
      "nbEtiquettes":1,
      "codeAllee":"7",
      "codeGondole":"J",
      "codeEmplacement":0,
      "typeCommande":"2",
      "typeFlux":"1",
      "strate":"M",
      "stockMinimum":2,
      "pvm":5.35,
      "stockMiniAutomatique":false,
      "labelCalculAutoStockMiniFamille":"2 - Stock Mini Max",
      "labelLongCalculAutoStockMiniFamille":"MAX(Fac*Ht*Pf//Vmh/NbLive sem)",
      "parametrageCalculAutoStockMiniFamille":false,
      "parametrageCalculAutoStockMiniArticle":true
   },
   {
      "typeArticle":"G",
      "codeArticle":"0988751",
      "libelleArticle":"CAPRI SUN ORANGE 10X20CL      ",
      "formatEtiquette":"G",
      "nbEtiquettes":1,
      "codeAllee":"W",
      "codeGondole":"C",
      "codeEmplacement":310,
      "typeCommande":"1",
      "typeFlux":"1",
      "strate":"S",
      "stockMinimum":2,
      "pvm":3.08,
      "stockMiniAutomatique":true,
      "labelCalculAutoStockMiniFamille":"1 - Stock Mini FHP",
      "labelLongCalculAutoStockMiniFamille":"Facing*Hauteur*Profondeur",
      "parametrageCalculAutoStockMiniFamille":true,
      "parametrageCalculAutoStockMiniArticle":true
   },
   {
      "typeArticle":"G",
      "codeArticle":"1445325",
      "libelleArticle":"CUILLERES A DESSERT INOX X6   ",
      "formatEtiquette":"P",
      "nbEtiquettes":1,
      "codeAllee":"C",
      "codeGondole":"I",
      "codeEmplacement":480,
      "typeCommande":"1",
      "typeFlux":"1",
      "strate":"S",
      "stockMinimum":6,
      "pvm":1.29,
      "stockMiniAutomatique":true,
      "labelCalculAutoStockMiniFamille":"1 - Stock Mini FHP",
      "labelLongCalculAutoStockMiniFamille":"Facing*Hauteur*Profondeur",
      "parametrageCalculAutoStockMiniFamille":true,
      "parametrageCalculAutoStockMiniArticle":true
   },
   {
      "typeArticle":"G",
      "codeArticle":"1445326",
      "libelleArticle":"CUILLERES A SOUPE INOX X6     ",
      "formatEtiquette":"P",
      "nbEtiquettes":1,
      "codeAllee":"C",
      "codeGondole":"I",
      "codeEmplacement":490,
      "typeCommande":"1",
      "typeFlux":"1",
      "strate":"S",
      "stockMinimum":6,
      "pvm":1.79,
      "stockMiniAutomatique":true,
      "labelCalculAutoStockMiniFamille":"1 - Stock Mini FHP",
      "labelLongCalculAutoStockMiniFamille":"Facing*Hauteur*Profondeur",
      "parametrageCalculAutoStockMiniFamille":true,
      "parametrageCalculAutoStockMiniArticle":true
   },
   {
      "typeArticle":"G",
      "codeArticle":"1445333",
      "libelleArticle":"CUILLERE A CAFE INTUITION LAGU",
      "formatEtiquette":"P",
      "nbEtiquettes":1,
      "codeAllee":"C",
      "codeGondole":"I",
      "codeEmplacement":400,
      "typeCommande":"1",
      "typeFlux":"1",
      "strate":"P",
      "stockMinimum":6,
      "pvm":2.39,
      "stockMiniAutomatique":true,
      "labelCalculAutoStockMiniFamille":"1 - Stock Mini FHP",
      "labelLongCalculAutoStockMiniFamille":"Facing*Hauteur*Profondeur",
      "parametrageCalculAutoStockMiniFamille":true,
      "parametrageCalculAutoStockMiniArticle":true
   },
   {
      "typeArticle":"G",
      "codeArticle":"1445752",
      "libelleArticle":"COUTEAU UNION JACK            ",
      "formatEtiquette":"P",
      "nbEtiquettes":1,
      "codeAllee":"C",
      "codeGondole":"I",
      "codeEmplacement":360,
      "typeCommande":"1",
      "typeFlux":"1",
      "strate":"P",
      "stockMinimum":6,
      "pvm":2.29,
      "stockMiniAutomatique":true,
      "labelCalculAutoStockMiniFamille":"1 - Stock Mini FHP",
      "labelLongCalculAutoStockMiniFamille":"Facing*Hauteur*Profondeur",
      "parametrageCalculAutoStockMiniFamille":true,
      "parametrageCalculAutoStockMiniArticle":true
   },
   {
      "typeArticle":"G",
      "codeArticle":"1445760",
      "libelleArticle":"PETITE CUILLÈRE UNION JACK    ",
      "formatEtiquette":"P",
      "nbEtiquettes":1,
      "codeAllee":"C",
      "codeGondole":"I",
      "codeEmplacement":390,
      "typeCommande":"1",
      "typeFlux":"1",
      "strate":"P",
      "stockMinimum":6,
      "pvm":1.99,
      "stockMiniAutomatique":true,
      "labelCalculAutoStockMiniFamille":"1 - Stock Mini FHP",
      "labelLongCalculAutoStockMiniFamille":"Facing*Hauteur*Profondeur",
      "parametrageCalculAutoStockMiniFamille":true,
      "parametrageCalculAutoStockMiniArticle":true
   },
   {
      "typeArticle":"G",
      "codeArticle":"1445780",
      "libelleArticle":"COUTEAU KOBE                  ",
      "formatEtiquette":"P",
      "nbEtiquettes":1,
      "codeAllee":"C",
      "codeGondole":"I",
      "codeEmplacement":270,
      "typeCommande":"1",
      "typeFlux":"1",
      "strate":"P",
      "stockMinimum":6,
      "pvm":2.29,
      "stockMiniAutomatique":true,
      "labelCalculAutoStockMiniFamille":"1 - Stock Mini FHP",
      "labelLongCalculAutoStockMiniFamille":"Facing*Hauteur*Profondeur",
      "parametrageCalculAutoStockMiniFamille":true,
      "parametrageCalculAutoStockMiniArticle":true
   },
   {
      "typeArticle":"G",
      "codeArticle":"1501278",
      "libelleArticle":"CUILLERE DIANE INOX           ",
      "formatEtiquette":"P",
      "nbEtiquettes":1,
      "codeAllee":"C",
      "codeGondole":"I",
      "codeEmplacement":330,
      "typeCommande":"1",
      "typeFlux":"1",
      "strate":"P",
      "stockMinimum":6,
      "pvm":2.39,
      "stockMiniAutomatique":true,
      "labelCalculAutoStockMiniFamille":"1 - Stock Mini FHP",
      "labelLongCalculAutoStockMiniFamille":"Facing*Hauteur*Profondeur",
      "parametrageCalculAutoStockMiniFamille":true,
      "parametrageCalculAutoStockMiniArticle":true
   },
   {
      "typeArticle":"G",
      "codeArticle":"1501279",
      "libelleArticle":"CUILLERE POIS GRIS            ",
      "formatEtiquette":"P",
      "nbEtiquettes":1,
      "codeAllee":"C",
      "codeGondole":"I",
      "codeEmplacement":460,
      "typeCommande":"1",
      "typeFlux":"1",
      "strate":"P",
      "stockMinimum":6,
      "pvm":1.29,
      "stockMiniAutomatique":true,
      "labelCalculAutoStockMiniFamille":"1 - Stock Mini FHP",
      "labelLongCalculAutoStockMiniFamille":"Facing*Hauteur*Profondeur",
      "parametrageCalculAutoStockMiniFamille":true,
      "parametrageCalculAutoStockMiniArticle":true
   },
   {
      "typeArticle":"G",
      "codeArticle":"1445328",
      "libelleArticle":"FOURCHETTES INOX X6           ",
      "formatEtiquette":"P",
      "nbEtiquettes":1,
      "codeAllee":"C",
      "codeGondole":"I",
      "codeEmplacement":500,
      "typeCommande":"1",
      "typeFlux":"1",
      "strate":"S",
      "stockMinimum":6,
      "pvm":1.79,
      "stockMiniAutomatique":true,
      "labelCalculAutoStockMiniFamille":"1 - Stock Mini FHP",
      "labelLongCalculAutoStockMiniFamille":"Facing*Hauteur*Profondeur",
      "parametrageCalculAutoStockMiniFamille":true,
      "parametrageCalculAutoStockMiniArticle":true
   },
   {
      "typeArticle":"G",
      "codeArticle":"1445329",
      "libelleArticle":"COUTEAUX INOX                 ",
      "formatEtiquette":"P",
      "nbEtiquettes":1,
      "codeAllee":"C",
      "codeGondole":"I",
      "codeEmplacement":510,
      "typeCommande":"1",
      "typeFlux":"1",
      "strate":"S",
      "stockMinimum":6,
      "pvm":0.79,
      "stockMiniAutomatique":true,
      "labelCalculAutoStockMiniFamille":"1 - Stock Mini FHP",
      "labelLongCalculAutoStockMiniFamille":"Facing*Hauteur*Profondeur",
      "parametrageCalculAutoStockMiniFamille":true,
      "parametrageCalculAutoStockMiniArticle":true
   },
   {
      "typeArticle":"G",
      "codeArticle":"1445331",
      "libelleArticle":"FOURCHETTE  INTUITION LAGUIOLE",
      "formatEtiquette":"P",
      "nbEtiquettes":1,
      "codeAllee":"C",
      "codeGondole":"I",
      "codeEmplacement":420,
      "typeCommande":"1",
      "typeFlux":"1",
      "strate":"P",
      "stockMinimum":6,
      "pvm":2.59,
      "stockMiniAutomatique":true,
      "labelCalculAutoStockMiniFamille":"1 - Stock Mini FHP",
      "labelLongCalculAutoStockMiniFamille":"Facing*Hauteur*Profondeur",
      "parametrageCalculAutoStockMiniFamille":true,
      "parametrageCalculAutoStockMiniArticle":true
   },
   {
      "typeArticle":"G",
      "codeArticle":"1445332",
      "libelleArticle":"CUILLERE  INTUITION LAGUIOLE B",
      "formatEtiquette":"P",
      "nbEtiquettes":1,
      "codeAllee":"C",
      "codeGondole":"I",
      "codeEmplacement":410,
      "typeCommande":"1",
      "typeFlux":"1",
      "strate":"P",
      "stockMinimum":6,
      "pvm":2.59,
      "stockMiniAutomatique":true,
      "labelCalculAutoStockMiniFamille":"1 - Stock Mini FHP",
      "labelLongCalculAutoStockMiniFamille":"Facing*Hauteur*Profondeur",
      "parametrageCalculAutoStockMiniFamille":true,
      "parametrageCalculAutoStockMiniArticle":true
   },
   {
      "typeArticle":"G",
      "codeArticle":"1445336",
      "libelleArticle":"FOURCHETTE POIS CLASSIC ROUGE ",
      "formatEtiquette":"P",
      "nbEtiquettes":1,
      "codeAllee":"C",
      "codeGondole":"I",
      "codeEmplacement":290,
      "typeCommande":"1",
      "typeFlux":"1",
      "strate":"P",
      "stockMinimum":6,
      "pvm":1.29,
      "stockMiniAutomatique":true,
      "labelCalculAutoStockMiniFamille":"1 - Stock Mini FHP",
      "labelLongCalculAutoStockMiniFamille":"Facing*Hauteur*Profondeur",
      "parametrageCalculAutoStockMiniFamille":true,
      "parametrageCalculAutoStockMiniArticle":true
   },
   {
      "typeArticle":"G",
      "codeArticle":"1445756",
      "libelleArticle":"FOURCHETTE UNION JACK         ",
      "formatEtiquette":"P",
      "nbEtiquettes":1,
      "codeAllee":"C",
      "codeGondole":"I",
      "codeEmplacement":370,
      "typeCommande":"1",
      "typeFlux":"1",
      "strate":"P",
      "stockMinimum":6,
      "pvm":2.29,
      "stockMiniAutomatique":true,
      "labelCalculAutoStockMiniFamille":"1 - Stock Mini FHP",
      "labelLongCalculAutoStockMiniFamille":"Facing*Hauteur*Profondeur",
      "parametrageCalculAutoStockMiniFamille":true,
      "parametrageCalculAutoStockMiniArticle":true
   },
   {
      "typeArticle":"G",
      "codeArticle":"1445782",
      "libelleArticle":"FOURCHETTE KOBE               ",
      "formatEtiquette":"P",
      "nbEtiquettes":1,
      "codeAllee":"C",
      "codeGondole":"I",
      "codeEmplacement":260,
      "typeCommande":"1",
      "typeFlux":"1",
      "strate":"P",
      "stockMinimum":6,
      "pvm":1.99,
      "stockMiniAutomatique":true,
      "labelCalculAutoStockMiniFamille":"1 - Stock Mini FHP",
      "labelLongCalculAutoStockMiniFamille":"Facing*Hauteur*Profondeur",
      "parametrageCalculAutoStockMiniFamille":true,
      "parametrageCalculAutoStockMiniArticle":true
   },
   {
      "typeArticle":"G",
      "codeArticle":"1445785",
      "libelleArticle":"CUILLÈRE KOBE                 ",
      "formatEtiquette":"P",
      "nbEtiquettes":1,
      "codeAllee":"C",
      "codeGondole":"I",
      "codeEmplacement":250,
      "typeCommande":"1",
      "typeFlux":"1",
      "strate":"P",
      "stockMinimum":6,
      "pvm":1.99,
      "stockMiniAutomatique":true,
      "labelCalculAutoStockMiniFamille":"1 - Stock Mini FHP",
      "labelLongCalculAutoStockMiniFamille":"Facing*Hauteur*Profondeur",
      "parametrageCalculAutoStockMiniFamille":true,
      "parametrageCalculAutoStockMiniArticle":true
   },
   {
      "typeArticle":"G",
      "codeArticle":"1501280",
      "libelleArticle":"FOURCHETTE DIANE INOX         ",
      "formatEtiquette":"P",
      "nbEtiquettes":1,
      "codeAllee":"C",
      "codeGondole":"I",
      "codeEmplacement":340,
      "typeCommande":"1",
      "typeFlux":"1",
      "strate":"P",
      "stockMinimum":6,
      "pvm":2.39,
      "stockMiniAutomatique":true,
      "labelCalculAutoStockMiniFamille":"1 - Stock Mini FHP",
      "labelLongCalculAutoStockMiniFamille":"Facing*Hauteur*Profondeur",
      "parametrageCalculAutoStockMiniFamille":true,
      "parametrageCalculAutoStockMiniArticle":true
   },
   {
      "typeArticle":"G",
      "codeArticle":"1501282",
      "libelleArticle":"FOURCHETTE POIS GRIS          ",
      "formatEtiquette":"P",
      "nbEtiquettes":1,
      "codeAllee":"C",
      "codeGondole":"I",
      "codeEmplacement":450,
      "typeCommande":"1",
      "typeFlux":"1",
      "strate":"P",
      "stockMinimum":6,
      "pvm":1.29,
      "stockMiniAutomatique":true,
      "labelCalculAutoStockMiniFamille":"1 - Stock Mini FHP",
      "labelLongCalculAutoStockMiniFamille":"Facing*Hauteur*Profondeur",
      "parametrageCalculAutoStockMiniFamille":true,
      "parametrageCalculAutoStockMiniArticle":true
   },
   {
      "typeArticle":"G",
      "codeArticle":"1445330",
      "libelleArticle":"COUTEAU INTUITION LAGUIOLE BLA",
      "formatEtiquette":"P",
      "nbEtiquettes":1,
      "codeAllee":"C",
      "codeGondole":"I",
      "codeEmplacement":430,
      "typeCommande":"1",
      "typeFlux":"1",
      "strate":"P",
      "stockMinimum":6,
      "pvm":2.59,
      "stockMiniAutomatique":true,
      "labelCalculAutoStockMiniFamille":"1 - Stock Mini FHP",
      "labelLongCalculAutoStockMiniFamille":"Facing*Hauteur*Profondeur",
      "parametrageCalculAutoStockMiniFamille":true,
      "parametrageCalculAutoStockMiniArticle":true
   },
   {
      "typeArticle":"G",
      "codeArticle":"1445334",
      "libelleArticle":"COUTEAU POIS CLASSIC ROUGE    ",
      "formatEtiquette":"P",
      "nbEtiquettes":1,
      "codeAllee":"C",
      "codeGondole":"I",
      "codeEmplacement":280,
      "typeCommande":"1",
      "typeFlux":"1",
      "strate":"P",
      "stockMinimum":6,
      "pvm":1.29,
      "stockMiniAutomatique":true,
      "labelCalculAutoStockMiniFamille":"1 - Stock Mini FHP",
      "labelLongCalculAutoStockMiniFamille":"Facing*Hauteur*Profondeur",
      "parametrageCalculAutoStockMiniFamille":true,
      "parametrageCalculAutoStockMiniArticle":true
   },
   {
      "typeArticle":"G",
      "codeArticle":"1501274",
      "libelleArticle":"COUTEAU DIANE INOX            ",
      "formatEtiquette":"P",
      "nbEtiquettes":1,
      "codeAllee":"C",
      "codeGondole":"I",
      "codeEmplacement":350,
      "typeCommande":"1",
      "typeFlux":"1",
      "strate":"P",
      "stockMinimum":6,
      "pvm":2.39,
      "stockMiniAutomatique":true,
      "labelCalculAutoStockMiniFamille":"1 - Stock Mini FHP",
      "labelLongCalculAutoStockMiniFamille":"Facing*Hauteur*Profondeur",
      "parametrageCalculAutoStockMiniFamille":true,
      "parametrageCalculAutoStockMiniArticle":true
   },
   {
      "typeArticle":"G",
      "codeArticle":"1501275",
      "libelleArticle":"COUTEAU POIS GRIS             ",
      "formatEtiquette":"P",
      "nbEtiquettes":1,
      "codeAllee":"C",
      "codeGondole":"I",
      "codeEmplacement":440,
      "typeCommande":"1",
      "typeFlux":"1",
      "strate":"S",
      "stockMinimum":6,
      "pvm":1.29,
      "stockMiniAutomatique":true,
      "labelCalculAutoStockMiniFamille":"1 - Stock Mini FHP",
      "labelLongCalculAutoStockMiniFamille":"Facing*Hauteur*Profondeur",
      "parametrageCalculAutoStockMiniFamille":true,
      "parametrageCalculAutoStockMiniArticle":true
   },
   {
      "typeArticle":"G",
      "codeArticle":"1445337",
      "libelleArticle":"CUILLERE POIS CLASSIC ROUGE   ",
      "formatEtiquette":"P",
      "nbEtiquettes":1,
      "codeAllee":"C",
      "codeGondole":"I",
      "codeEmplacement":300,
      "typeCommande":"1",
      "typeFlux":"1",
      "strate":"P",
      "stockMinimum":6,
      "pvm":1.29,
      "stockMiniAutomatique":true,
      "labelCalculAutoStockMiniFamille":"1 - Stock Mini FHP",
      "labelLongCalculAutoStockMiniFamille":"Facing*Hauteur*Profondeur",
      "parametrageCalculAutoStockMiniFamille":true,
      "parametrageCalculAutoStockMiniArticle":true
   },
   {
      "typeArticle":"G",
      "codeArticle":"1445338",
      "libelleArticle":"CUILLERE A CAFE POIS CLASSIC  ",
      "formatEtiquette":"P",
      "nbEtiquettes":1,
      "codeAllee":"C",
      "codeGondole":"I",
      "codeEmplacement":310,
      "typeCommande":"1",
      "typeFlux":"1",
      "strate":"P",
      "stockMinimum":6,
      "pvm":1.0,
      "stockMiniAutomatique":true,
      "labelCalculAutoStockMiniFamille":"1 - Stock Mini FHP",
      "labelLongCalculAutoStockMiniFamille":"Facing*Hauteur*Profondeur",
      "parametrageCalculAutoStockMiniFamille":true,
      "parametrageCalculAutoStockMiniArticle":true
   },
   {
      "typeArticle":"G",
      "codeArticle":"1445758",
      "libelleArticle":"CUILLÈRE UNION JACK           ",
      "formatEtiquette":"P",
      "nbEtiquettes":1,
      "codeAllee":"C",
      "codeGondole":"I",
      "codeEmplacement":380,
      "typeCommande":"1",
      "typeFlux":"1",
      "strate":"P",
      "stockMinimum":6,
      "pvm":2.29,
      "stockMiniAutomatique":true,
      "labelCalculAutoStockMiniFamille":"1 - Stock Mini FHP",
      "labelLongCalculAutoStockMiniFamille":"Facing*Hauteur*Profondeur",
      "parametrageCalculAutoStockMiniFamille":true,
      "parametrageCalculAutoStockMiniArticle":true
   },
   {
      "typeArticle":"G",
      "codeArticle":"1501276",
      "libelleArticle":"CUILLERE A CAFE DIANE INOX    ",
      "formatEtiquette":"P",
      "nbEtiquettes":1,
      "codeAllee":"C",
      "codeGondole":"I",
      "codeEmplacement":320,
      "typeCommande":"1",
      "typeFlux":"1",
      "strate":"P",
      "stockMinimum":6,
      "pvm":2.39,
      "stockMiniAutomatique":true,
      "labelCalculAutoStockMiniFamille":"1 - Stock Mini FHP",
      "labelLongCalculAutoStockMiniFamille":"Facing*Hauteur*Profondeur",
      "parametrageCalculAutoStockMiniFamille":true,
      "parametrageCalculAutoStockMiniArticle":true
   },
   {
      "typeArticle":"G",
      "codeArticle":"1501277",
      "libelleArticle":"CUILLERE CAFE POIS GRIS       ",
      "formatEtiquette":"P",
      "nbEtiquettes":1,
      "codeAllee":"C",
      "codeGondole":"I",
      "codeEmplacement":470,
      "typeCommande":"1",
      "typeFlux":"1",
      "strate":"S",
      "stockMinimum":6,
      "pvm":1.0,
      "stockMiniAutomatique":true,
      "labelCalculAutoStockMiniFamille":"1 - Stock Mini FHP",
      "labelLongCalculAutoStockMiniFamille":"Facing*Hauteur*Profondeur",
      "parametrageCalculAutoStockMiniFamille":true,
      "parametrageCalculAutoStockMiniArticle":true
   },
   {
      "typeArticle":"G",
      "codeArticle":"1445322",
      "libelleArticle":"MENAGERE 24PCES RETRO BLANC   ",
      "formatEtiquette":"G",
      "nbEtiquettes":1,
      "codeAllee":"C",
      "codeGondole":"I",
      "codeEmplacement":230,
      "typeCommande":"1",
      "typeFlux":"1",
      "strate":"P",
      "stockMinimum":1,
      "pvm":8.99,
      "stockMiniAutomatique":true,
      "labelCalculAutoStockMiniFamille":"1 - Stock Mini FHP",
      "labelLongCalculAutoStockMiniFamille":"Facing*Hauteur*Profondeur",
      "parametrageCalculAutoStockMiniFamille":true,
      "parametrageCalculAutoStockMiniArticle":true
   },
   {
      "typeArticle":"G",
      "codeArticle":"1445320",
      "libelleArticle":"MENAGERE 16PCS MULTICOLOR POIS",
      "formatEtiquette":"P",
      "nbEtiquettes":1,
      "codeAllee":"C",
      "codeGondole":"I",
      "codeEmplacement":235,
      "typeCommande":"1",
      "typeFlux":"1",
      "strate":"M",
      "stockMinimum":2,
      "pvm":13.9,
      "stockMiniAutomatique":true,
      "labelCalculAutoStockMiniFamille":"1 - Stock Mini FHP",
      "labelLongCalculAutoStockMiniFamille":"Facing*Hauteur*Profondeur",
      "parametrageCalculAutoStockMiniFamille":true,
      "parametrageCalculAutoStockMiniArticle":true
   },
   {
      "typeArticle":"G",
      "codeArticle":"1414953",
      "libelleArticle":"PATE AU JAMBON FORET NOIRE    ",
      "formatEtiquette":"G",
      "nbEtiquettes":1,
      "codeAllee":"7",
      "codeGondole":"E",
      "codeEmplacement":0,
      "typeCommande":"2",
      "typeFlux":"1",
      "strate":"P",
      "stockMinimum":2,
      "pvm":17.2,
      "stockMiniAutomatique":false,
      "labelCalculAutoStockMiniFamille":"2 - Stock Mini Max",
      "labelLongCalculAutoStockMiniFamille":"MAX(Fac*Ht*Pf//Vmh/NbLive sem)",
      "parametrageCalculAutoStockMiniFamille":false,
      "parametrageCalculAutoStockMiniArticle":true
   }
]
